tspkg/ARCH_AIC.txt
tspkg/Intro.txt
tspkg/TS_code.txt
tspkg/__init__.py
tspkg/codepack.py
tspkg/models.txt
tspkg/tests_plots.txt
tspkg-0.1.dist-info/METADATA
tspkg-0.1.dist-info/WHEEL
tspkg-0.1.dist-info/licenses/LICENSE
tspkg-0.1.dist-info/RECORD
