Metadata-Version: 2.1
Name: tspkg
Version: 0.1
Summary: Life's difficult
Author-email: Anonymous <author@example.com>
License-File: LICENSE
Classifier: License :: OSI Approved :: MIT License
Classifier: Operating System :: OS Independent
Classifier: Programming Language :: Python :: 3
Requires-Python: >=3.7
